MANIFEST.in
README.rst
setup.cfg
setup.py
crosscompute_select/__init__.py
crosscompute_select/type.jinja2
crosscompute_select.egg-info/PKG-INFO
crosscompute_select.egg-info/SOURCES.txt
crosscompute_select.egg-info/dependency_links.txt
crosscompute_select.egg-info/entry_points.txt
crosscompute_select.egg-info/not-zip-safe
crosscompute_select.egg-info/requires.txt
crosscompute_select.egg-info/top_level.txt
crosscompute_select/assets/part.min.css
crosscompute_select/assets/part.min.js