Metadata-Version: 1.1
Name: crosscompute-select
Version: 0.7.5
Summary: Select tag data type plugin for CrossCompute
Home-page: https://github.com/salah93/crosscompute-select
Author: Salah Ahmed
Author-email: salah93@crosscompute.com
License: UNKNOWN
Keywords: web pyramid pylons crosscompute
Platform: UNKNOWN
Classifier: Programming Language :: Python
Classifier: Framework :: Pyramid
Classifier: Topic :: Internet :: WWW/HTTP :: WSGI :: Application
Classifier: License :: OSI Approved :: MIT License
